databar_utility/__init__.py
databar_utility/databar.py
databar_utility/databar_2.py
databar_utility/tushare_utility.py
general_utility/MyEncoder.py
general_utility/__init__.py
general_utility/appbase.py
general_utility/bootutils.py
general_utility/importutils.py
general_utility/logger.py
general_utility/utils.py
general_utility/ftptool/__init__.py
general_utility/ftptool/ftptool.py
general_utility/ftptool/setup.py
general_utility/ftptool/test.py
general_utility/smtptool/__init__.py
general_utility/smtptool/smtptool.py
plugin_utility/__init__.py
plugin_utility/iplugin.py
plugin_utility/plugin_manager.py
plugin_utility/plugin_object.py
plugin_utility/test.py
atoml_utility-2.3.4.10.dist-info/METADATA
atoml_utility-2.3.4.10.dist-info/WHEEL
atoml_utility-2.3.4.10.dist-info/top_level.txt
atoml_utility-2.3.4.10.dist-info/RECORD
