Metadata-Version: 2.1
Name: atoml-utility
Version: 2.3.4.10
Summary: atoml ct system utility.
Home-page: https://atoml.com/
Author: caijun
Author-email: caijun@atoml.com
License: MIT
Classifier: License :: OSI Approved :: MIT License
Classifier: Programming Language :: Python
Classifier: Programming Language :: Python :: 3
Classifier: Programming Language :: Python :: 3.6
Classifier: Programming Language :: Python :: Implementation :: CPython
Classifier: Programming Language :: Python :: Implementation :: PyPy
Requires-Python: >=3.6.0
Requires-Dist: requests (<=2.27.1,>=2.16.0)
